[
  {
    "id": "jee-main",
    "name": "Joint Entrance Examination (Main)",
    "shortName": "JEE Main",
    "type": "Engineering UG",
    "category": "Engineering",
    "logo": "https://upload.wikimedia.org/wikipedia/commons/thumb/b/bb/JEE_Main_logo.svg/1200px-JEE_Main_logo.svg.png",
    "conductingBody": "National Testing Agency (NTA)",
    "stats": {
      "applicants": "12.5 Lakhs",
      "fee": " 1000",
      "duration": "3 Hours",
      "mode": "Online (CBT)"
    },
    "markingScheme": {
      "correct": "+4",
      "incorrect": "-1"
    },
    "safeScore": {
      "min": "90+ %ile",
      "target": "NITs/IIITs"
    },
    "courses": [
      "B.E./B.Tech",
      "B.Arch",
      "B.Planning"
    ],
    "pattern": [
      "Paper 1: Physics, Chemistry, Mathematics (MCQ + Numerical)",
      "Paper 2A: Mathematics, Aptitude, Drawing",
      "Paper 2B: Mathematics, Aptitude, Planning"
    ],
    "totalMarks": "300 (B.Tech)",
    "dates": {
      "registration": "Session 1: Nov-Dec 2025; Session 2: Feb-Mar 2026",
      "examWindow": "Session 1: Jan 2026; Session 2: Apr 2026",
      "result": "Feb 2026 / May 2026"
    },
    "pastPapers": [
      {
        "label": "Official Question Papers",
        "url": "https://jeemain.nta.ac.in/archive"
      }
    ],
    "prepResources": [
      {
        "title": "NCERT Physics & Chemistry is Bible",
        "type": "Tip"
      },
      {
        "title": "Focus on PYQs (2019-2024)",
        "type": "Strategy"
      }
    ],
    "officialUrl": "https://jeemain.nta.ac.in",
    "collegesAccepting": [
      "nit-trichy",
      "nit-warangal",
      "iiit-hyderabad",
      "delhi-technological-university",
      "netaji-subhas-university-of-technology",
      "ict-mumbai"
    ]
  },
  {
    "id": "jee-advanced",
    "name": "Joint Entrance Examination (Advanced)",
    "shortName": "JEE Advanced",
    "type": "Engineering UG",
    "category": "Engineering",
    "logo": "https://jeeadv.ac.in/logos/JEE-Advanced-Logo.png",
    "conductingBody": "IITs (Rotational)",
    "stats": {
      "applicants": "1.9 Lakhs",
      "fee": " 3200",
      "duration": "6 Hours (2 Papers)",
      "mode": "Online (CBT)"
    },
    "markingScheme": {
      "correct": "+3 / +4",
      "incorrect": "-1 / -2"
    },
    "safeScore": {
      "min": "30% (Qualifying)",
      "target": "IITs"
    },
    "courses": [
      "B.Tech",
      "BS",
      "Dual Degree (B.Tech + M.Tech)"
    ],
    "pattern": [
      "Paper 1 & 2: Physics, Chemistry, Mathematics (Mixed types: MCQ, Numerical, Matrix Match)"
    ],
    "totalMarks": "Varies yearly (typically 360 or 306)",
    "dates": {
      "registration": "April-May 2026",
      "examWindow": "May 2026 (Last Sunday)",
      "result": "June 2026"
    },
    "pastPapers": [
      {
        "label": "Past Question Papers",
        "url": "https://jeeadv.ac.in/archive.html"
      }
    ],
    "officialUrl": "https://jeeadv.ac.in",
    "collegesAccepting": [
      "iit-bombay",
      "iit-delhi",
      "iit-madras",
      "iit-kanpur",
      "iit-kharagpur",
      "iit-roorkee",
      "iisc-bengaluru",
      "iiser-pune"
    ]
  },
  {
    "id": "neet-ug",
    "name": "National Eligibility cum Entrance Test (Undergraduate)",
    "shortName": "NEET UG",
    "type": "Medical UG",
    "category": "Medical",
    "logo": "https://upload.wikimedia.org/wikipedia/en/2/27/NEET_UG_logo.png",
    "conductingBody": "National Testing Agency (NTA)",
    "stats": {
      "applicants": "24 Lakhs",
      "fee": " 1700",
      "duration": "3 Hours 20 Mins",
      "mode": "Offline (Pen & Paper)"
    },
    "markingScheme": {
      "correct": "+4",
      "incorrect": "-1"
    },
    "safeScore": {
      "min": "600+",
      "target": "Govt Medical Colleges"
    },
    "courses": [
      "MBBS",
      "BDS",
      "BAMS",
      "BHMS",
      "B.Sc Nursing (selected institutes)"
    ],
    "pattern": [
      "Physics (45 Q)",
      "Chemistry (45 Q)",
      "Biology (Botany+Zoology 90 Q)"
    ],
    "totalMarks": "720",
    "dates": {
      "registration": "March-April 2026",
      "examWindow": "May 2026 (First Sunday)",
      "result": "June 2026"
    },
    "pastPapers": [
      {
        "label": "Archive",
        "url": "https://exams.nta.ac.in/NEET/"
      }
    ],
    "officialUrl": "https://exams.nta.ac.in/NEET/",
    "collegesAccepting": [
      "aiims-new-delhi",
      "cmc-vellore",
      "jipmer-puducherry",
      "kgmu-lucknow",
      "mmc-chennai",
      "afmc-pune"
    ]
  },
  {
    "id": "cuet-ug",
    "name": "Common University Entrance Test (Undergraduate)",
    "shortName": "CUET-UG",
    "type": "General UG",
    "category": "General",
    "logo": "https://cdnbbsr.s3waas.gov.in/s3547842b0a688688c27931341c2c2f152/uploads/2021/04/2021040582.png",
    "conductingBody": "National Testing Agency (NTA)",
    "stats": {
      "applicants": "15 Lakhs",
      "fee": " 800 (per subject)",
      "duration": "Various Slots",
      "mode": "Hybrid (CBT + Pen Paper)"
    },
    "markingScheme": {
      "correct": "+5",
      "incorrect": "-1"
    },
    "safeScore": {
      "min": "95+ %ile",
      "target": "DU North Campus"
    },
    "courses": [
      "B.A.",
      "B.Sc",
      "B.Com",
      "BBA",
      "Integrated Programs"
    ],
    "pattern": [
      "Section IA/IB: Languages",
      "Section II: Domain Subjects",
      "Section III: General Test"
    ],
    "totalMarks": "Varies based on subject combination",
    "dates": {
      "registration": "Feb-March 2026",
      "examWindow": "May 2026",
      "result": "July 2026"
    },
    "pastPapers": [
      {
        "label": "Mock Tests",
        "url": "https://exams.nta.ac.in/CUET-UG/"
      }
    ],
    "officialUrl": "https://exams.nta.ac.in/CUET-UG/",
    "collegesAccepting": [
      "delhi-university",
      "jnu-delhi",
      "bhu-varanasi",
      "uoh-hyderabad",
      "tiss-mumbai"
    ]
  },
  {
    "id": "gate",
    "name": "Graduate Aptitude Test in Engineering",
    "shortName": "GATE",
    "type": "Engineering PG",
    "category": "Engineering",
    "logo": "https://gate2025.iitr.ac.in/assets/images/logo_gate2025.svg",
    "conductingBody": "IISc & IITs (Rotational)",
    "stats": {
      "applicants": "8.5 Lakhs",
      "fee": " 1800",
      "duration": "3 Hours",
      "mode": "Online (CBT)"
    },
    "markingScheme": {
      "correct": "+1 / +2",
      "incorrect": "-1/3 / -2/3"
    },
    "safeScore": {
      "min": "Score 600+",
      "target": "IIT M.Tech / PSUs"
    },
    "courses": [
      "M.Tech",
      "Ph.D",
      "PSU Recruitment"
    ],
    "pattern": [
      "General Aptitude (15 marks)",
      "Subject Questions (85 marks)"
    ],
    "totalMarks": "100",
    "dates": {
      "registration": "Aug-Sept 2025",
      "examWindow": "Feb 2026 (First two weekends)",
      "result": "March 2026"
    },
    "pastPapers": [
      {
        "label": "Previous Papers",
        "url": "https://gate.iitk.ac.in"
      }
    ],
    "officialUrl": "https://gate.iitk.ac.in",
    "collegesAccepting": [
      "iit-bombay",
      "iisc-bengaluru",
      "nit-trichy",
      "jadavpur-university",
      "delhi-technological-university"
    ]
  },
  {
    "id": "cat",
    "name": "Common Admission Test",
    "shortName": "CAT",
    "type": "Management",
    "category": "Management",
    "logo": "https://iimcat.ac.in/per/g06/pub/32842/ASM/WebPortal/1/images/cat-logo.png",
    "conductingBody": "IIMs (Rotational)",
    "stats": {
      "applicants": "3.3 Lakhs",
      "fee": " 2400",
      "duration": "2 Hours",
      "mode": "Online (CBT)"
    },
    "markingScheme": {
      "correct": "+3",
      "incorrect": "-1 (MCQ)"
    },
    "safeScore": {
      "min": "98+ %ile",
      "target": "BLACKIA IIMs"
    },
    "courses": [
      "MBA",
      "PGDM",
      "Fellow Programs"
    ],
    "pattern": [
      "VARC (40 Mins)",
      "DILR (40 Mins)",
      "QA (40 Mins)"
    ],
    "totalMarks": "198 (approx)",
    "dates": {
      "registration": "Aug-Sept 2025",
      "examWindow": "Nov 2025 (Last Sunday)",
      "result": "Dec 2025 / Jan 2026"
    },
    "pastPapers": [
      {
        "label": "Mock Test",
        "url": "https://iimcat.ac.in"
      }
    ],
    "officialUrl": "https://iimcat.ac.in",
    "collegesAccepting": [
      "iim-ahmedabad",
      "iim-bangalore",
      "iim-calcutta",
      "fms-delhi",
      "spjimr-mumbai",
      "iit-delhi-dms"
    ]
  },
  {
    "id": "clat",
    "name": "Common Law Admission Test",
    "shortName": "CLAT",
    "type": "Law",
    "category": "Law",
    "logo": "https://consortiumofnlus.ac.in/clat-2024/img/clat-2024-logo.png",
    "conductingBody": "Consortium of NLUs",
    "stats": {
      "applicants": "60,000+",
      "fee": " 4000",
      "duration": "2 Hours",
      "mode": "Offline"
    },
    "markingScheme": {
      "correct": "+1",
      "incorrect": "-0.25"
    },
    "safeScore": {
      "min": "90+",
      "target": "Top 3 NLUs"
    },
    "courses": [
      "B.A. LL.B.",
      "B.B.A. LL.B.",
      "LL.M."
    ],
    "pattern": [
      "English",
      "Current Affairs",
      "Legal Reasoning",
      "Logical Reasoning",
      "Quant"
    ],
    "totalMarks": "120",
    "dates": {
      "registration": "July-Oct 2025",
      "examWindow": "Dec 2025",
      "result": "Dec 2025"
    },
    "pastPapers": [
      {
        "label": "Sample Papers",
        "url": "https://consortiumofnlus.ac.in"
      }
    ],
    "officialUrl": "https://consortiumofnlus.ac.in",
    "collegesAccepting": [
      "nlsiu-bengaluru",
      "nalsar-hyderabad",
      "nujs-kolkata",
      "nliu-bhopal",
      "gnlu-gandhinagar"
    ]
  },
  {
    "id": "bitsat",
    "name": "Birla Institute of Technology and Science Admission Test",
    "shortName": "BITSAT",
    "type": "Engineering UG",
    "category": "Engineering",
    "logo": "https://www.bitsadmission.com/images/bits-logo.png",
    "conductingBody": "BITS Pilani",
    "stats": {
      "applicants": "3 Lakhs",
      "fee": " 5400 (Both Sessions)",
      "duration": "3 Hours",
      "mode": "Online (CBT)"
    },
    "markingScheme": {
      "correct": "+3",
      "incorrect": "-1"
    },
    "safeScore": {
      "min": "300+",
      "target": "BITS Pilani CS"
    },
    "courses": [
      "B.E. (Hons)",
      "B.Pharm",
      "M.Sc (Hons)"
    ],
    "pattern": [
      "Physics, Chemistry, English, Logical Reasoning, Mathematics/Biology"
    ],
    "totalMarks": "390",
    "dates": {
      "registration": "Jan-April 2026",
      "examWindow": "May-June 2026",
      "result": "June 2026"
    },
    "pastPapers": [],
    "officialUrl": "https://www.bitsadmission.com",
    "collegesAccepting": [
      "bits-pilani",
      "bits-goa",
      "bits-hyderabad"
    ]
  },
  {
    "id": "vit-eee",
    "name": "VIT Engineering Entrance Examination",
    "shortName": "VITEEE",
    "type": "Engineering UG",
    "category": "Engineering",
    "logo": "https://vit.ac.in/sites/default/files/logo-5.png",
    "conductingBody": "Vellore Institute of Technology",
    "stats": {
      "applicants": "2 Lakhs+",
      "fee": " 1350",
      "duration": "2.5 Hours",
      "mode": "Online (CBT)"
    },
    "markingScheme": {
      "correct": "+1",
      "incorrect": "No Negative"
    },
    "safeScore": {
      "min": "Rank < 5000",
      "target": "VIT Vellore CS"
    },
    "courses": [
      "B.Tech"
    ],
    "pattern": [
      "Maths/Biology, Physics, Chemistry, English, Aptitude"
    ],
    "totalMarks": "125",
    "dates": {
      "registration": "Nov 2025 - Mar 2026",
      "examWindow": "April 2026",
      "result": "May 2026"
    },
    "pastPapers": [],
    "officialUrl": "https://vit.ac.in",
    "collegesAccepting": [
      "vit-vellore",
      "vit-chennai",
      "vit-ap",
      "vit-bhopal"
    ]
  },
  {
    "id": "wbjee",
    "name": "West Bengal Joint Entrance Examination",
    "shortName": "WBJEE",
    "type": "Engineering UG",
    "category": "Engineering",
    "logo": "https://wbjeeb.nic.in/wp-content/themes/sdo-theme/images/emblem.png",
    "conductingBody": "WBJEEB",
    "stats": {
      "applicants": "1 Lakh+",
      "fee": " 500",
      "duration": "4 Hours (2 Papers)",
      "mode": "Offline"
    },
    "markingScheme": {
      "correct": "Category wise",
      "incorrect": "-1/4 (Cat 1)"
    },
    "safeScore": {
      "min": "130+",
      "target": "Jadavpur Uni"
    },
    "courses": [
      "B.E./B.Tech",
      "B.Pharm",
      "B.Arch"
    ],
    "pattern": [
      "Mathematics (100 marks)",
      "Physics & Chemistry (100 marks)"
    ],
    "totalMarks": "200",
    "dates": {
      "registration": "Dec 2025 - Jan 2026",
      "examWindow": "April 2026",
      "result": "May 2026"
    },
    "pastPapers": [
      {
        "label": "Old Papers",
        "url": "https://wbjeeb.nic.in"
      }
    ],
    "officialUrl": "https://wbjeeb.nic.in",
    "collegesAccepting": [
      "jadavpur-university",
      "calcutta-university",
      "kalyani-government-engineering-college",
      "iem-kolkata",
      "heritage-institute-technology"
    ]
  },
  {
    "id": "mht-cet",
    "name": "Maharashtra Common Entrance Test",
    "shortName": "MHT CET",
    "type": "Engineering/Pharmacy",
    "category": "Engineering",
    "conductingBody": "State Common Entrance Test Cell, Maharashtra",
    "courses": [
      "B.E./B.Tech",
      "B.Pharm",
      "Pharm.D",
      "B.Sc Agriculture"
    ],
    "pattern": [
      "PCM or PCB Group (Maths/Bio 100 marks, Phy+Chem 100 marks)"
    ],
    "totalMarks": "200",
    "dates": {
      "registration": "Feb-March 2026",
      "examWindow": "May 2026",
      "result": "June 2026"
    },
    "pastPapers": [],
    "officialUrl": "https://cetcell.mahacet.org",
    "collegesAccepting": [
      "coep-pune",
      "vjti-mumbai",
      "ict-mumbai",
      "spit-mumbai",
      "walchand-sangli"
    ]
  },
  {
    "id": "kcet",
    "name": "Karnataka Common Entrance Test",
    "shortName": "KCET",
    "type": "State Entrance",
    "category": "Engineering",
    "conductingBody": "Karnataka Examinations Authority (KEA)",
    "courses": [
      "B.E./B.Tech",
      "B.Pharm",
      "B.Sc Agriculture",
      "B.V.Sc"
    ],
    "pattern": [
      "Physics, Chemistry, Mathematics/Biology (60 marks each)"
    ],
    "totalMarks": "180 (PCM)",
    "dates": {
      "registration": "Feb-March 2026",
      "examWindow": "April 2026",
      "result": "May 2026"
    },
    "pastPapers": [
      {
        "label": "Previous Papers",
        "url": "https://cetonline.karnataka.gov.in/kea/"
      }
    ],
    "officialUrl": "https://cetonline.karnataka.gov.in/kea/",
    "collegesAccepting": [
      "rv-college-of-engineering",
      "bms-college-of-engineering",
      "ms-ramaiah-institute-of-technology",
      "pes-university",
      "university-visvesvaraya-college-of-engineering"
    ]
  },
  {
    "id": "comedk-uget",
    "name": "Consortium of Medical, Engineering and Dental Colleges of Karnataka UGET",
    "shortName": "COMEDK UGET",
    "type": "Engineering UG",
    "category": "Engineering",
    "conductingBody": "COMEDK",
    "courses": [
      "B.E./B.Tech"
    ],
    "pattern": [
      "Physics (60), Chemistry (60), Mathematics (60)"
    ],
    "totalMarks": "180",
    "dates": {
      "registration": "Feb-April 2026",
      "examWindow": "May 2026",
      "result": "May 2026"
    },
    "pastPapers": [],
    "officialUrl": "https://www.comedk.org",
    "collegesAccepting": [
      "nift-bengaluru",
      "nift-bengaluru",
      "nift-bengaluru",
      "siddaganga-institute-of-technology",
      "nit-mizoram"
    ]
  },
  {
    "id": "ts-eamcet",
    "name": "Telangana State Engineering, Agriculture & Medical Common Entrance Test",
    "shortName": "TS EAPCET",
    "type": "State Entrance",
    "category": "Engineering",
    "conductingBody": "JNTU Hyderabad (on behalf of TSCHE)",
    "courses": [
      "B.Tech",
      "B.Sc Agriculture",
      "B.Pharm"
    ],
    "pattern": [
      "Mathematics (80), Physics (40), Chemistry (40)"
    ],
    "totalMarks": "160",
    "dates": {
      "registration": "Feb-April 2026",
      "examWindow": "May 2026",
      "result": "May 2026"
    },
    "pastPapers": [],
    "officialUrl": "https://eapcet.tsche.ac.in",
    "collegesAccepting": [
      "jntu-hyderabad",
      "osmania-university",
      "iiit-hyderabad",
      "vnr-vignana-jyothi-institute-of-engineering-and-technology",
      "aditya-engineering-college"
    ]
  },
  {
    "id": "ap-eamcet",
    "name": "Andhra Pradesh Engineering, Agriculture and Pharmacy Common Entrance Test",
    "shortName": "AP EAPCET",
    "type": "State Entrance",
    "category": "Engineering",
    "conductingBody": "JNTU Kakinada (on behalf of APSCHE)",
    "courses": [
      "B.Tech",
      "B.Sc Agriculture",
      "B.Pharm"
    ],
    "pattern": [
      "Mathematics (80), Physics (40), Chemistry (40)"
    ],
    "totalMarks": "160",
    "dates": {
      "registration": "March-April 2026",
      "examWindow": "May 2026",
      "result": "June 2026"
    },
    "pastPapers": [],
    "officialUrl": "https://cets.apsche.ap.gov.in",
    "collegesAccepting": [
      "gitam-visakhapatnam",
      "svu-tirupati",
      "jntu-kakinada",
      "jntu-anantapur",
      "gayatri-vidya-parishad"
    ]
  },
  {
    "id": "keam",
    "name": "Kerala Engineering Architecture Medical",
    "shortName": "KEAM",
    "type": "State Entrance",
    "category": "Engineering",
    "conductingBody": "CEE Kerala",
    "courses": [
      "B.Tech",
      "B.Pharm",
      "B.Arch (Score used)",
      "MBBS (Score used)"
    ],
    "pattern": [
      "Paper 1: Physics & Chemistry",
      "Paper 2: Mathematics"
    ],
    "totalMarks": "960",
    "dates": {
      "registration": "March-April 2026",
      "examWindow": "May 2026",
      "result": "June 2026"
    },
    "pastPapers": [
      {
        "label": "Previous Question Papers",
        "url": "https://cee.kerala.gov.in"
      }
    ],
    "officialUrl": "https://cee.kerala.gov.in",
    "collegesAccepting": [
      "sctimst-trivandrum",
      "model-engineering-college-thrikkakara",
      "kerala-university-of-health-sciences",
      "tkm-college-of-engineering",
      "mahatma-gandhi-university-kerala"
    ]
  },
  {
    "id": "nata",
    "name": "National Aptitude Test in Architecture",
    "shortName": "NATA",
    "type": "Architecture",
    "category": "Architecture",
    "conductingBody": "Council of Architecture (CoA)",
    "courses": [
      "B.Arch"
    ],
    "pattern": [
      "Drawing and Observation",
      "PCM",
      "General Aptitude"
    ],
    "totalMarks": "200",
    "dates": {
      "registration": "March 2026 onwards (Multiple attempts)",
      "examWindow": "April - July 2026 (Weekends)",
      "result": "Within a week of test"
    },
    "pastPapers": [],
    "officialUrl": "https://www.nata.in",
    "collegesAccepting": [
      "au-ahmedabad",
      "nm-college-mumbai",
      "sir-jj-architecture",
      "sushant-school-architecture",
      "chandigarh-college-of-architecture"
    ]
  },
  {
    "id": "uceed",
    "name": "Undergraduate Common Entrance Examination for Design",
    "shortName": "UCEED",
    "type": "Design",
    "category": "Design",
    "conductingBody": "IIT Bombay",
    "courses": [
      "B.Des"
    ],
    "pattern": [
      "Part A (Computer Based): Visualization, Spatial Ability",
      "Part B (Pen & Paper): Drawing"
    ],
    "totalMarks": "300",
    "dates": {
      "registration": "Oct-Nov 2025",
      "examWindow": "Jan 2026",
      "result": "March 2026"
    },
    "pastPapers": [
      {
        "label": "Past Papers",
        "url": "https://www.uceed.iitb.ac.in"
      }
    ],
    "officialUrl": "https://www.uceed.iitb.ac.in",
    "collegesAccepting": [
      "iit-bombay",
      "iit-delhi",
      "iit-guwahati",
      "iit-hyderabad",
      "iiit-bhagalpur",
      "iiit-delhi"
    ]
  },
  {
    "id": "nift-entrance",
    "name": "NIFT Entrance Examination",
    "shortName": "NIFT EE",
    "type": "Design",
    "category": "Design",
    "conductingBody": "National Testing Agency (NTA) / NIFT",
    "courses": [
      "B.Des",
      "B.F.Tech",
      "M.Des",
      "M.F.M"
    ],
    "pattern": [
      "GAT (General Ability Test)",
      "CAT (Creative Ability Test)",
      "Situation Test"
    ],
    "totalMarks": "Weighted Score",
    "dates": {
      "registration": "Dec 2025 - Jan 2026",
      "examWindow": "Feb 2026",
      "result": "March 2026"
    },
    "pastPapers": [],
    "officialUrl": "https://nift.ac.in/admission",
    "collegesAccepting": [
      "iiit-delhi",
      "ict-mumbai",
      "nift-bengaluru",
      "nift-bengaluru",
      "iit-gandhinagar"
    ]
  },
  {
    "id": "xat",
    "name": "Xavier Aptitude Test",
    "shortName": "XAT",
    "type": "Management",
    "category": "Management",
    "conductingBody": "XLRI Jamshedpur",
    "courses": [
      "MBA",
      "PGDM"
    ],
    "pattern": [
      "Verbal & Logical Ability",
      "Decision Making",
      "QA & DI",
      "GK & Essay"
    ],
    "totalMarks": "100 (approx)",
    "dates": {
      "registration": "Aug-Nov 2025",
      "examWindow": "Jan 2026 (First Sunday)",
      "result": "Jan 2026"
    },
    "pastPapers": [],
    "officialUrl": "https://xatonline.in",
    "collegesAccepting": [
      "xlri-jamshedpur",
      "aiims-bhubaneswar",
      "goa-institute-of-management",
      "sikkim-manipal-university",
      "kiet-ghaziabad"
    ]
  },
  {
    "id": "mat",
    "name": "Management Aptitude Test",
    "shortName": "MAT",
    "type": "Management",
    "category": "Management",
    "conductingBody": "AIMA",
    "courses": [
      "MBA",
      "PGDM"
    ],
    "pattern": [
      "Language Comprehension",
      "Mathematical Skills",
      "Data Analysis",
      "Intelligence",
      "Indian Global Environment"
    ],
    "totalMarks": "200",
    "dates": {
      "registration": "Feb, May, Sept, Dec (Multiple Sessions)",
      "examWindow": "Feb, May, Sept, Dec",
      "result": "End of respective month"
    },
    "pastPapers": [],
    "officialUrl": "https://mat.aima.in",
    "collegesAccepting": [
      "jiit-noida",
      "christ-university-bengaluru",
      "pgims-rohtak",
      "iiit-hyderabad"
    ]
  },
  {
    "id": "cmat",
    "name": "Common Management Admission Test",
    "shortName": "CMAT",
    "type": "Management",
    "category": "Management",
    "conductingBody": "National Testing Agency (NTA)",
    "courses": [
      "MBA",
      "PGDM"
    ],
    "pattern": [
      "QA & DI",
      "Logical Reasoning",
      "Language Comprehension",
      "GK",
      "Innovation & Entrepreneurship"
    ],
    "totalMarks": "400",
    "dates": {
      "registration": "Feb-March 2026",
      "examWindow": "April/May 2026",
      "result": "May 2026"
    },
    "pastPapers": [],
    "officialUrl": "https://cmat.nta.nic.in",
    "collegesAccepting": [
      "iim-mumbai",
      "simsree-mumbai",
      "great-lakes-gurgaon",
      "kj-somaiya-mumbai",
      "pumba-pune"
    ]
  },
  {
    "id": "snap",
    "name": "Symbiosis National Aptitude Test",
    "shortName": "SNAP",
    "type": "Management",
    "category": "Management",
    "conductingBody": "Symbiosis International (Deemed University)",
    "courses": [
      "MBA"
    ],
    "pattern": [
      "General English",
      "Analytical & Logical Reasoning",
      "QA, DI & DS"
    ],
    "totalMarks": "60",
    "dates": {
      "registration": "Aug-Nov 2025",
      "examWindow": "Dec 2025 (Three dates)",
      "result": "Jan 2026"
    },
    "pastPapers": [],
    "officialUrl": "https://www.snaptest.org",
    "collegesAccepting": [
      "symbiosis-pune",
      "iiser-pune",
      "iit-pune",
      "nift-bengaluru"
    ]
  },
  {
    "id": "nmat",
    "name": "NMAT by GMAC",
    "shortName": "NMAT",
    "type": "Management",
    "category": "Management",
    "conductingBody": "Graduate Management Admission Council",
    "courses": [
      "MBA",
      "PGDM"
    ],
    "pattern": [
      "Language Skills",
      "Quantitative Skills",
      "Logical Reasoning"
    ],
    "totalMarks": "360 (Scaled)",
    "dates": {
      "registration": "Aug-Oct 2025",
      "examWindow": "Oct-Dec 2025 (Adaptive window)",
      "result": "Within 48 hours of exam"
    },
    "pastPapers": [],
    "officialUrl": "https://www.nmat.org",
    "collegesAccepting": [
      "nmims-mumbai",
      "kj-somaiya-mumbai",
      "tapmi-manipal"
    ]
  }
]
